{
  "platforms": {
    "arduino_uno": {
      "id": "arduino_uno",
      "name": "Arduino Uno",
      "mcu": "ATmega328P",
      "clockSpeed": "16MHz",
      "flashMemory": "32KB",
      "sram": "2KB",
      "operatingVoltage": 5,
      "logicLevel": 5,
      "maxCurrentPerPin": 40,
      "maxCurrentTotal": 200,
      "hasWifi": false,
      "hasBluetooth": false,
      "pins": [
        { "id": "D0", "name": "D0", "gpio": 0, "capabilities": ["digital", "uart_rx"], "reserved": true, "reservedFor": "Serial RX" },
        { "id": "D1", "name": "D1", "gpio": 1, "capabilities": ["digital", "uart_tx"], "reserved": true, "reservedFor": "Serial TX" },
        { "id": "D2", "name": "D2", "gpio": 2, "capabilities": ["digital", "interrupt"] },
        { "id": "D3", "name": "D3", "gpio": 3, "capabilities": ["digital", "pwm", "interrupt"] },
        { "id": "D4", "name": "D4", "gpio": 4, "capabilities": ["digital"] },
        { "id": "D5", "name": "D5", "gpio": 5, "capabilities": ["digital", "pwm"] },
        { "id": "D6", "name": "D6", "gpio": 6, "capabilities": ["digital", "pwm"] },
        { "id": "D7", "name": "D7", "gpio": 7, "capabilities": ["digital"] },
        { "id": "D8", "name": "D8", "gpio": 8, "capabilities": ["digital"] },
        { "id": "D9", "name": "D9", "gpio": 9, "capabilities": ["digital", "pwm"] },
        { "id": "D10", "name": "D10", "gpio": 10, "capabilities": ["digital", "pwm", "spi_ss"] },
        { "id": "D11", "name": "D11", "gpio": 11, "capabilities": ["digital", "pwm", "spi_mosi"] },
        { "id": "D12", "name": "D12", "gpio": 12, "capabilities": ["digital", "spi_miso"] },
        { "id": "D13", "name": "D13", "gpio": 13, "capabilities": ["digital", "spi_sck", "led_builtin"] },
        { "id": "A0", "name": "A0", "gpio": 14, "capabilities": ["analog", "digital"], "analogChannel": 0 },
        { "id": "A1", "name": "A1", "gpio": 15, "capabilities": ["analog", "digital"], "analogChannel": 1 },
        { "id": "A2", "name": "A2", "gpio": 16, "capabilities": ["analog", "digital"], "analogChannel": 2 },
        { "id": "A3", "name": "A3", "gpio": 17, "capabilities": ["analog", "digital"], "analogChannel": 3 },
        { "id": "A4", "name": "A4", "gpio": 18, "capabilities": ["analog", "digital", "i2c_sda"], "analogChannel": 4 },
        { "id": "A5", "name": "A5", "gpio": 19, "capabilities": ["analog", "digital", "i2c_scl"], "analogChannel": 5 }
      ],
      "powerPins": [
        { "name": "5V", "voltage": 5 },
        { "name": "3.3V", "voltage": 3.3 },
        { "name": "GND", "voltage": 0 },
        { "name": "VIN", "voltage": "7-12V" }
      ],
      "i2c": { "sda": "A4", "scl": "A5" },
      "spi": { "mosi": "D11", "miso": "D12", "sck": "D13", "ss": "D10" },
      "uart": { "tx": "D1", "rx": "D0" },
      "boardDimensions": { "width": 68.6, "height": 53.4 }
    },
    "esp32": {
      "id": "esp32",
      "name": "ESP32 DevKit",
      "mcu": "ESP32-WROOM-32",
      "clockSpeed": "240MHz",
      "flashMemory": "4MB",
      "sram": "520KB",
      "operatingVoltage": 3.3,
      "logicLevel": 3.3,
      "maxCurrentPerPin": 40,
      "maxCurrentTotal": 1200,
      "hasWifi": true,
      "hasBluetooth": true,
      "pins": [
        { "id": "GPIO0", "name": "GPIO0", "gpio": 0, "capabilities": ["digital", "pwm", "touch", "adc2"], "reserved": true, "reservedFor": "Boot" },
        { "id": "GPIO2", "name": "GPIO2", "gpio": 2, "capabilities": ["digital", "pwm", "touch", "adc2", "led_builtin"] },
        { "id": "GPIO4", "name": "GPIO4", "gpio": 4, "capabilities": ["digital", "pwm", "touch", "adc2"] },
        { "id": "GPIO5", "name": "GPIO5", "gpio": 5, "capabilities": ["digital", "pwm", "spi_ss"] },
        { "id": "GPIO12", "name": "GPIO12", "gpio": 12, "capabilities": ["digital", "pwm", "touch", "adc2"], "reserved": true, "reservedFor": "Boot strapping" },
        { "id": "GPIO13", "name": "GPIO13", "gpio": 13, "capabilities": ["digital", "pwm", "touch", "adc2"] },
        { "id": "GPIO14", "name": "GPIO14", "gpio": 14, "capabilities": ["digital", "pwm", "touch", "adc2"] },
        { "id": "GPIO15", "name": "GPIO15", "gpio": 15, "capabilities": ["digital", "pwm", "touch", "adc2"] },
        { "id": "GPIO16", "name": "GPIO16", "gpio": 16, "capabilities": ["digital", "pwm", "uart_rx2"] },
        { "id": "GPIO17", "name": "GPIO17", "gpio": 17, "capabilities": ["digital", "pwm", "uart_tx2"] },
        { "id": "GPIO18", "name": "GPIO18", "gpio": 18, "capabilities": ["digital", "pwm", "spi_sck"] },
        { "id": "GPIO19", "name": "GPIO19", "gpio": 19, "capabilities": ["digital", "pwm", "spi_miso"] },
        { "id": "GPIO21", "name": "GPIO21", "gpio": 21, "capabilities": ["digital", "pwm", "i2c_sda"] },
        { "id": "GPIO22", "name": "GPIO22", "gpio": 22, "capabilities": ["digital", "pwm", "i2c_scl"] },
        { "id": "GPIO23", "name": "GPIO23", "gpio": 23, "capabilities": ["digital", "pwm", "spi_mosi"] },
        { "id": "GPIO25", "name": "GPIO25", "gpio": 25, "capabilities": ["digital", "pwm", "adc2", "dac1"] },
        { "id": "GPIO26", "name": "GPIO26", "gpio": 26, "capabilities": ["digital", "pwm", "adc2", "dac2"] },
        { "id": "GPIO27", "name": "GPIO27", "gpio": 27, "capabilities": ["digital", "pwm", "touch", "adc2"] },
        { "id": "GPIO32", "name": "GPIO32", "gpio": 32, "capabilities": ["digital", "pwm", "touch", "adc1"] },
        { "id": "GPIO33", "name": "GPIO33", "gpio": 33, "capabilities": ["digital", "pwm", "touch", "adc1"] },
        { "id": "GPIO34", "name": "GPIO34", "gpio": 34, "capabilities": ["digital", "adc1"], "inputOnly": true },
        { "id": "GPIO35", "name": "GPIO35", "gpio": 35, "capabilities": ["digital", "adc1"], "inputOnly": true },
        { "id": "GPIO36", "name": "SVP/GPIO36", "gpio": 36, "capabilities": ["analog", "adc1"], "inputOnly": true },
        { "id": "GPIO39", "name": "SVN/GPIO39", "gpio": 39, "capabilities": ["analog", "adc1"], "inputOnly": true }
      ],
      "powerPins": [
        { "name": "3V3", "voltage": 3.3 },
        { "name": "5V", "voltage": 5 },
        { "name": "GND", "voltage": 0 },
        { "name": "VIN", "voltage": "5V via USB" }
      ],
      "i2c": { "sda": "GPIO21", "scl": "GPIO22" },
      "spi": { "mosi": "GPIO23", "miso": "GPIO19", "sck": "GPIO18", "ss": "GPIO5" },
      "uart": { "tx": "GPIO1", "rx": "GPIO3" },
      "uart2": { "tx": "GPIO17", "rx": "GPIO16" },
      "boardDimensions": { "width": 55, "height": 28 }
    },
    "esp8266": {
      "id": "esp8266",
      "name": "ESP8266 NodeMCU",
      "mcu": "ESP8266",
      "clockSpeed": "80MHz",
      "flashMemory": "4MB",
      "sram": "80KB",
      "operatingVoltage": 3.3,
      "logicLevel": 3.3,
      "maxCurrentPerPin": 12,
      "maxCurrentTotal": 400,
      "hasWifi": true,
      "hasBluetooth": false,
      "pins": [
        { "id": "D0", "name": "D0/GPIO16", "gpio": 16, "capabilities": ["digital"], "notes": "No PWM, no interrupt" },
        { "id": "D1", "name": "D1/GPIO5", "gpio": 5, "capabilities": ["digital", "pwm", "i2c_scl"] },
        { "id": "D2", "name": "D2/GPIO4", "gpio": 4, "capabilities": ["digital", "pwm", "i2c_sda"] },
        { "id": "D3", "name": "D3/GPIO0", "gpio": 0, "capabilities": ["digital", "pwm"], "reserved": true, "reservedFor": "Boot (must be HIGH)" },
        { "id": "D4", "name": "D4/GPIO2", "gpio": 2, "capabilities": ["digital", "pwm", "led_builtin"], "reserved": true, "reservedFor": "Boot (must be HIGH)" },
        { "id": "D5", "name": "D5/GPIO14", "gpio": 14, "capabilities": ["digital", "pwm", "spi_sck"] },
        { "id": "D6", "name": "D6/GPIO12", "gpio": 12, "capabilities": ["digital", "pwm", "spi_miso"] },
        { "id": "D7", "name": "D7/GPIO13", "gpio": 13, "capabilities": ["digital", "pwm", "spi_mosi"] },
        { "id": "D8", "name": "D8/GPIO15", "gpio": 15, "capabilities": ["digital", "pwm", "spi_ss"], "reserved": true, "reservedFor": "Boot (must be LOW)" },
        { "id": "A0", "name": "A0", "gpio": null, "capabilities": ["analog"], "analogChannel": 0, "maxVoltage": 1.0, "notes": "0-1V input range" }
      ],
      "powerPins": [
        { "name": "3V3", "voltage": 3.3 },
        { "name": "5V", "voltage": 5 },
        { "name": "GND", "voltage": 0 },
        { "name": "VIN", "voltage": "5V via USB" }
      ],
      "i2c": { "sda": "D2", "scl": "D1" },
      "spi": { "mosi": "D7", "miso": "D6", "sck": "D5", "ss": "D8" },
      "uart": { "tx": "GPIO1", "rx": "GPIO3" },
      "boardDimensions": { "width": 58, "height": 31 },
      "notes": "Only 1 analog pin (A0), limited GPIO count"
    },
    "arduino_nano": {
      "id": "arduino_nano",
      "name": "Arduino Nano",
      "mcu": "ATmega328P",
      "clockSpeed": "16MHz",
      "flashMemory": "32KB",
      "sram": "2KB",
      "operatingVoltage": 5,
      "logicLevel": 5,
      "maxCurrentPerPin": 40,
      "maxCurrentTotal": 200,
      "hasWifi": false,
      "hasBluetooth": false,
      "pins": [
        { "id": "D2", "name": "D2", "gpio": 2, "capabilities": ["digital", "interrupt"] },
        { "id": "D3", "name": "D3", "gpio": 3, "capabilities": ["digital", "pwm", "interrupt"] },
        { "id": "D4", "name": "D4", "gpio": 4, "capabilities": ["digital"] },
        { "id": "D5", "name": "D5", "gpio": 5, "capabilities": ["digital", "pwm"] },
        { "id": "D6", "name": "D6", "gpio": 6, "capabilities": ["digital", "pwm"] },
        { "id": "D7", "name": "D7", "gpio": 7, "capabilities": ["digital"] },
        { "id": "D8", "name": "D8", "gpio": 8, "capabilities": ["digital"] },
        { "id": "D9", "name": "D9", "gpio": 9, "capabilities": ["digital", "pwm"] },
        { "id": "D10", "name": "D10", "gpio": 10, "capabilities": ["digital", "pwm", "spi_ss"] },
        { "id": "D11", "name": "D11", "gpio": 11, "capabilities": ["digital", "pwm", "spi_mosi"] },
        { "id": "D12", "name": "D12", "gpio": 12, "capabilities": ["digital", "spi_miso"] },
        { "id": "D13", "name": "D13", "gpio": 13, "capabilities": ["digital", "spi_sck", "led_builtin"] },
        { "id": "A0", "name": "A0", "gpio": 14, "capabilities": ["analog", "digital"], "analogChannel": 0 },
        { "id": "A1", "name": "A1", "gpio": 15, "capabilities": ["analog", "digital"], "analogChannel": 1 },
        { "id": "A2", "name": "A2", "gpio": 16, "capabilities": ["analog", "digital"], "analogChannel": 2 },
        { "id": "A3", "name": "A3", "gpio": 17, "capabilities": ["analog", "digital"], "analogChannel": 3 },
        { "id": "A4", "name": "A4", "gpio": 18, "capabilities": ["analog", "digital", "i2c_sda"], "analogChannel": 4 },
        { "id": "A5", "name": "A5", "gpio": 19, "capabilities": ["analog", "digital", "i2c_scl"], "analogChannel": 5 },
        { "id": "A6", "name": "A6", "gpio": 20, "capabilities": ["analog"], "analogChannel": 6, "inputOnly": true },
        { "id": "A7", "name": "A7", "gpio": 21, "capabilities": ["analog"], "analogChannel": 7, "inputOnly": true }
      ],
      "powerPins": [
        { "name": "3V3", "voltage": 3.3 },
        { "name": "5V", "voltage": 5 },
        { "name": "GND", "voltage": 0 },
        { "name": "VIN", "voltage": "7-12V" }
      ],
      "i2c": { "sda": "A4", "scl": "A5" },
      "spi": { "mosi": "D11", "miso": "D12", "sck": "D13", "ss": "D10" },
      "uart": { "tx": "D1", "rx": "D0" },
      "boardDimensions": { "width": 45, "height": 18 }
    },
    "arduino_mega": {
      "id": "arduino_mega",
      "name": "Arduino Mega 2560",
      "mcu": "ATmega2560",
      "clockSpeed": "16MHz",
      "flashMemory": "256KB",
      "sram": "8KB",
      "operatingVoltage": 5,
      "logicLevel": 5,
      "hasWifi": false,
      "hasBluetooth": false,
      "pins": [
        { "id": "D2", "name": "D2", "gpio": 2, "capabilities": ["digital", "pwm", "interrupt"] },
        { "id": "D3", "name": "D3", "gpio": 3, "capabilities": ["digital", "pwm", "interrupt"] },
        { "id": "D18", "name": "D18/TX1", "gpio": 18, "capabilities": ["digital", "uart_tx", "interrupt"] },
        { "id": "D19", "name": "D19/RX1", "gpio": 19, "capabilities": ["digital", "uart_rx", "interrupt"] },
        { "id": "D20", "name": "D20/SDA", "gpio": 20, "capabilities": ["digital", "i2c_sda"] },
        { "id": "D21", "name": "D21/SCL", "gpio": 21, "capabilities": ["digital", "i2c_scl"] },
        { "id": "D50", "name": "D50/MISO", "gpio": 50, "capabilities": ["digital", "spi_miso"] },
        { "id": "D51", "name": "D51/MOSI", "gpio": 51, "capabilities": ["digital", "spi_mosi"] },
        { "id": "D52", "name": "D52/SCK", "gpio": 52, "capabilities": ["digital", "spi_sck"] },
        { "id": "D53", "name": "D53/SS", "gpio": 53, "capabilities": ["digital", "spi_ss"] },
        { "id": "A0", "name": "A0", "gpio": 54, "capabilities": ["analog", "digital"], "analogChannel": 0 },
        { "id": "A1", "name": "A1", "gpio": 55, "capabilities": ["analog", "digital"], "analogChannel": 1 },
        { "id": "A2", "name": "A2", "gpio": 56, "capabilities": ["analog", "digital"], "analogChannel": 2 },
        { "id": "A3", "name": "A3", "gpio": 57, "capabilities": ["analog", "digital"], "analogChannel": 3 },
        { "id": "A4", "name": "A4", "gpio": 58, "capabilities": ["analog", "digital"], "analogChannel": 4 },
        { "id": "A5", "name": "A5", "gpio": 59, "capabilities": ["analog", "digital"], "analogChannel": 5 },
        { "id": "A6", "name": "A6", "gpio": 60, "capabilities": ["analog", "digital"], "analogChannel": 6 },
        { "id": "A7", "name": "A7", "gpio": 61, "capabilities": ["analog", "digital"], "analogChannel": 7 },
        { "id": "A8", "name": "A8", "gpio": 62, "capabilities": ["analog", "digital"], "analogChannel": 8 },
        { "id": "A9", "name": "A9", "gpio": 63, "capabilities": ["analog", "digital"], "analogChannel": 9 },
        { "id": "A10", "name": "A10", "gpio": 64, "capabilities": ["analog", "digital"], "analogChannel": 10 },
        { "id": "A11", "name": "A11", "gpio": 65, "capabilities": ["analog", "digital"], "analogChannel": 11 },
        { "id": "A12", "name": "A12", "gpio": 66, "capabilities": ["analog", "digital"], "analogChannel": 12 },
        { "id": "A13", "name": "A13", "gpio": 67, "capabilities": ["analog", "digital"], "analogChannel": 13 },
        { "id": "A14", "name": "A14", "gpio": 68, "capabilities": ["analog", "digital"], "analogChannel": 14 },
        { "id": "A15", "name": "A15", "gpio": 69, "capabilities": ["analog", "digital"], "analogChannel": 15 }
      ],
      "powerPins": [
        { "name": "5V", "voltage": 5 },
        { "name": "3.3V", "voltage": 3.3 },
        { "name": "GND", "voltage": 0 },
        { "name": "VIN", "voltage": "7-12V" }
      ],
      "i2c": { "sda": "D20", "scl": "D21" },
      "spi": { "mosi": "D51", "miso": "D50", "sck": "D52", "ss": "D53" },
      "uart": { "tx": "D1", "rx": "D0" },
      "boardDimensions": { "width": 101.52, "height": 53.3 }
    },
    "stm32f103": {
      "id": "stm32f103",
      "name": "STM32 Blue Pill",
      "mcu": "STM32F103C8T6",
      "clockSpeed": "72MHz",
      "flashMemory": "64KB",
      "sram": "20KB",
      "operatingVoltage": 3.3,
      "logicLevel": 3.3,
      "hasWifi": false,
      "hasBluetooth": false,
      "pins": [
        { "id": "PA0", "name": "PA0", "gpio": 0, "capabilities": ["digital", "analog", "pwm", "interrupt"], "analogChannel": 0 },
        { "id": "PA1", "name": "PA1", "gpio": 1, "capabilities": ["digital", "analog", "pwm", "interrupt"], "analogChannel": 1 },
        { "id": "PA2", "name": "PA2", "gpio": 2, "capabilities": ["digital", "analog", "pwm", "uart_tx2", "interrupt"], "analogChannel": 2 },
        { "id": "PA3", "name": "PA3", "gpio": 3, "capabilities": ["digital", "analog", "pwm", "uart_rx2", "interrupt"], "analogChannel": 3 },
        { "id": "PA4", "name": "PA4", "gpio": 4, "capabilities": ["digital", "analog", "spi_ss1", "interrupt"], "analogChannel": 4 },
        { "id": "PA5", "name": "PA5", "gpio": 5, "capabilities": ["digital", "analog", "spi_sck1", "interrupt"], "analogChannel": 5 },
        { "id": "PA6", "name": "PA6", "gpio": 6, "capabilities": ["digital", "analog", "pwm", "spi_miso1", "interrupt"], "analogChannel": 6 },
        { "id": "PA7", "name": "PA7", "gpio": 7, "capabilities": ["digital", "analog", "pwm", "spi_mosi1", "interrupt"], "analogChannel": 7 },
        { "id": "PA8", "name": "PA8", "gpio": 8, "capabilities": ["digital", "pwm", "interrupt"] },
        { "id": "PA9", "name": "PA9", "gpio": 9, "capabilities": ["digital", "pwm", "uart_tx1", "interrupt"] },
        { "id": "PA10", "name": "PA10", "gpio": 10, "capabilities": ["digital", "pwm", "uart_rx1", "interrupt"] },
        { "id": "PB6", "name": "PB6", "gpio": 22, "capabilities": ["digital", "pwm", "i2c_scl1", "interrupt"] },
        { "id": "PB7", "name": "PB7", "gpio": 23, "capabilities": ["digital", "pwm", "i2c_sda1", "interrupt"] },
        { "id": "PC13", "name": "PC13", "gpio": 45, "capabilities": ["digital", "led_builtin"] }
      ],
      "powerPins": [
        { "name": "3.3V", "voltage": 3.3 },
        { "name": "5V", "voltage": 5 },
        { "name": "GND", "voltage": 0 }
      ],
      "i2c": { "sda": "PB7", "scl": "PB6" },
      "spi": { "mosi": "PA7", "miso": "PA6", "sck": "PA5", "ss": "PA4" },
      "uart": { "tx": "PA9", "rx": "PA10" },
      "boardDimensions": { "width": 53, "height": 22 }
    },
    "rpi_pico": {
      "id": "rpi_pico",
      "name": "Raspberry Pi Pico",
      "mcu": "RP2040",
      "clockSpeed": "133MHz",
      "flashMemory": "2MB",
      "sram": "264KB",
      "operatingVoltage": 3.3,
      "logicLevel": 3.3,
      "maxCurrentPerPin": 12,
      "maxCurrentTotal": 300,
      "hasWifi": false,
      "hasBluetooth": false,
      "pins": [
        { "id": "GP0", "name": "GP0", "gpio": 0, "capabilities": ["digital", "pwm", "uart_tx0", "i2c_sda0", "spi_miso0"] },
        { "id": "GP1", "name": "GP1", "gpio": 1, "capabilities": ["digital", "pwm", "uart_rx0", "i2c_scl0", "spi_ss0"] },
        { "id": "GP2", "name": "GP2", "gpio": 2, "capabilities": ["digital", "pwm", "i2c_sda1", "spi_sck0"] },
        { "id": "GP3", "name": "GP3", "gpio": 3, "capabilities": ["digital", "pwm", "i2c_scl1", "spi_mosi0"] },
        { "id": "GP4", "name": "GP4", "gpio": 4, "capabilities": ["digital", "pwm", "uart_tx1", "i2c_sda0", "spi_miso0"] },
        { "id": "GP5", "name": "GP5", "gpio": 5, "capabilities": ["digital", "pwm", "uart_rx1", "i2c_scl0", "spi_ss0"] },
        { "id": "GP6", "name": "GP6", "gpio": 6, "capabilities": ["digital", "pwm", "i2c_sda1", "spi_sck0"] },
        { "id": "GP7", "name": "GP7", "gpio": 7, "capabilities": ["digital", "pwm", "i2c_scl1", "spi_mosi0"] },
        { "id": "GP8", "name": "GP8", "gpio": 8, "capabilities": ["digital", "pwm", "uart_tx1", "i2c_sda0", "spi_miso1"] },
        { "id": "GP9", "name": "GP9", "gpio": 9, "capabilities": ["digital", "pwm", "uart_rx1", "i2c_scl0", "spi_ss1"] },
        { "id": "GP10", "name": "GP10", "gpio": 10, "capabilities": ["digital", "pwm", "i2c_sda1", "spi_sck1"] },
        { "id": "GP11", "name": "GP11", "gpio": 11, "capabilities": ["digital", "pwm", "i2c_scl1", "spi_mosi1"] },
        { "id": "GP12", "name": "GP12", "gpio": 12, "capabilities": ["digital", "pwm", "uart_tx0", "i2c_sda0", "spi_miso1"] },
        { "id": "GP13", "name": "GP13", "gpio": 13, "capabilities": ["digital", "pwm", "uart_rx0", "i2c_scl0", "spi_ss1"] },
        { "id": "GP14", "name": "GP14", "gpio": 14, "capabilities": ["digital", "pwm", "i2c_sda1", "spi_sck1"] },
        { "id": "GP15", "name": "GP15", "gpio": 15, "capabilities": ["digital", "pwm", "i2c_scl1", "spi_mosi1"] },
        { "id": "GP16", "name": "GP16", "gpio": 16, "capabilities": ["digital", "pwm", "spi_miso0"] },
        { "id": "GP17", "name": "GP17", "gpio": 17, "capabilities": ["digital", "pwm", "spi_ss0"] },
        { "id": "GP18", "name": "GP18", "gpio": 18, "capabilities": ["digital", "pwm", "spi_sck0"] },
        { "id": "GP19", "name": "GP19", "gpio": 19, "capabilities": ["digital", "pwm", "spi_mosi0"] },
        { "id": "GP20", "name": "GP20", "gpio": 20, "capabilities": ["digital", "pwm", "i2c_sda0"] },
        { "id": "GP21", "name": "GP21", "gpio": 21, "capabilities": ["digital", "pwm", "i2c_scl0"] },
        { "id": "GP22", "name": "GP22", "gpio": 22, "capabilities": ["digital", "pwm"] },
        { "id": "GP26", "name": "GP26/ADC0", "gpio": 26, "capabilities": ["digital", "pwm", "analog"], "analogChannel": 0 },
        { "id": "GP27", "name": "GP27/ADC1", "gpio": 27, "capabilities": ["digital", "pwm", "analog"], "analogChannel": 1 },
        { "id": "GP28", "name": "GP28/ADC2", "gpio": 28, "capabilities": ["digital", "pwm", "analog"], "analogChannel": 2 }
      ],
      "powerPins": [
        { "name": "3V3", "voltage": 3.3 },
        { "name": "VSYS", "voltage": 5 },
        { "name": "GND", "voltage": 0 },
        { "name": "VBUS", "voltage": "5V via USB" }
      ],
      "i2c": { "sda": "GP20", "scl": "GP21" },
      "spi": { "mosi": "GP19", "miso": "GP16", "sck": "GP18", "ss": "GP17" },
      "uart": { "tx": "GP0", "rx": "GP1" },
      "boardDimensions": { "width": 51, "height": 21 }
    },
    "attiny85": {
      "id": "attiny85",
      "name": "ATtiny85",
      "mcu": "ATtiny85",
      "clockSpeed": "8MHz",
      "flashMemory": "8KB",
      "sram": "512B",
      "operatingVoltage": 5,
      "logicLevel": 5,
      "maxCurrentPerPin": 40,
      "maxCurrentTotal": 200,
      "hasWifi": false,
      "hasBluetooth": false,
      "pins": [
        { "id": "PB0", "name": "PB0/D0", "gpio": 0, "capabilities": ["digital", "pwm", "spi_mosi"] },
        { "id": "PB1", "name": "PB1/D1", "gpio": 1, "capabilities": ["digital", "pwm", "spi_miso"] },
        { "id": "PB2", "name": "PB2/D2/A1", "gpio": 2, "capabilities": ["digital", "analog", "spi_sck", "i2c_scl"], "analogChannel": 1 },
        { "id": "PB3", "name": "PB3/D3/A3", "gpio": 3, "capabilities": ["digital", "analog"], "analogChannel": 3 },
        { "id": "PB4", "name": "PB4/D4/A2", "gpio": 4, "capabilities": ["digital", "analog", "pwm", "i2c_sda"], "analogChannel": 2 }
      ],
      "powerPins": [
        { "name": "VCC", "voltage": 5 },
        { "name": "GND", "voltage": 0 }
      ],
      "i2c": { "sda": "PB4", "scl": "PB2" },
      "spi": { "mosi": "PB0", "miso": "PB1", "sck": "PB2" },
      "boardDimensions": { "width": 10, "height": 10 },
      "notes": "Only 5 GPIO pins, very limited. Best for simple single-purpose devices."
    }
  }
}
